caret/__init__.py
caret/agi.py
caret/agitb.py
caret/config.py
caret/fastagi.py
caret/manager.py
caret-0.1.0.dist-info/DESCRIPTION.rst
caret-0.1.0.dist-info/METADATA
caret-0.1.0.dist-info/RECORD
caret-0.1.0.dist-info/WHEEL
caret-0.1.0.dist-info/metadata.json
caret-0.1.0.dist-info/top_level.txt
