Metadata-Version: 2.0
Name: caret
Version: 0.1.0
Summary: A Python Interface to Asterisk
Home-page: https://github.com/ar13pit/caret
Author: Arpit Aggarwal
Author-email: ar13pit@gmail.com
License: LGPL-3.0
Keywords: python asterisk agi ami telephony sip voip
Platform: Any
Classifier: Development Status :: 5 - Production/Stable
Classifier: Environment :: Other Environment
Classifier: Intended Audience :: Developers
Classifier: Intended Audience :: Telecommunications Industry
Classifier: Operating System :: OS Independent
Classifier: Programming Language :: Python
Classifier: Programming Language :: Python :: 2.7
Classifier: Programming Language :: Python :: 3
Classifier: Programming Language :: Python :: 3.5
Classifier: Programming Language :: Python :: 3.6
Classifier: Programming Language :: Python :: 3.7
Classifier: Topic :: Communications :: Internet Phone
Classifier: Topic :: Communications :: Telephony
Classifier: Topic :: Software Development :: Libraries :: Python Modules
Requires-Dist: Sphinx (>=1.6.3)
Requires-Dist: six (>=1.10.0)
Requires-Dist: sphinx-rtd-theme (>=0.2.4)
